pyhdfview/__init__.py
pyhdfview/cli.py
pyhdfview-0.2.dist-info/DESCRIPTION.rst
pyhdfview-0.2.dist-info/entry_points.txt
pyhdfview-0.2.dist-info/METADATA
pyhdfview-0.2.dist-info/metadata.json
pyhdfview-0.2.dist-info/RECORD
pyhdfview-0.2.dist-info/top_level.txt
pyhdfview-0.2.dist-info/WHEEL
