Metadata-Version: 2.0
Name: pyhdfview
Version: 0.2
Summary: A viewer for HDF5 files
Home-page: https://bitbucket.org/ssc/pyhdfview
Author: Stefan Scherfke
Author-email: stefan at sofa-rockers.org
License: UNKNOWN
Platform: UNKNOWN
Classifier: Development Status :: 3 - Alpha
Classifier: Environment :: Console
Classifier: Intended Audience :: Science/Research
Classifier: License :: OSI Approved :: MIT License
Classifier: Natural Language :: English
Classifier: Operating System :: OS Independent
Classifier: Programming Language :: Python
Classifier: Programming Language :: Python :: 3
Classifier: Programming Language :: Python :: 3.3
Classifier: Programming Language :: Python :: 3.4
Classifier: Topic :: Scientific/Engineering
Requires-Dist: colorama (>=0.3.2)
Requires-Dist: docopt (>=0.6.2)
Requires-Dist: h5py (>=2.3.1)
Requires-Dist: numpy (>=1.8.1)
